grai_source_cube/__init__.py
grai_source_cube/adapters.py
grai_source_cube/api.py
grai_source_cube/base.py
grai_source_cube/connector.py
grai_source_cube/mock_tools.py
grai_source_cube/package_definitions.py
grai_source_cube/settings.py
grai_source_cube/types.py
grai_source_cube-0.0.2.dist-info/METADATA
grai_source_cube-0.0.2.dist-info/WHEEL
grai_source_cube-0.0.2.dist-info/RECORD
